{
  "config": "flextrackv2_b224_56_abl_no_hallucinate",
  "RGBT234": {
    "mpr": 92.41,
    "msr": 69.45
  },
  "RGBT234_miss": {
    "mpr": 84.57,
    "msr": 62.68
  },
  "LasHeR": {
    "pr": 76.14,
    "sr": 61.03
  },
  "LasHeR_miss": {
    "pr": 67.36,
    "sr": 54.01
  },
  "VisEvent": {
    "auc": 65.69,
    "pr": 79.77
  },
  "VisEvent_miss": {
    "auc": 58.66,
    "pr": 73.35
  },
  "DepthTrack": {
    "precision": 63.89,
    "recall": 66.77,
    "fscore": 65.3
  },
  "DepthTrack_miss": {
    "precision": 56.11,
    "recall": 58.64,
    "fscore": 57.35
  }
}